README.md
setup.cfg
setup.py
Nepali_nlp/Download_embedding.py
Nepali_nlp/Embedding.py
Nepali_nlp/Nepali_tokenizer.py
Nepali_nlp/__init__.py
Nepali_nlp/fasttext_embedding.py
Nepali_nlp/n_gram.py
Nepali_nlp/news_latest.py
Nepali_nlp/news_scrap.py
Nepali_nlp/ocr.py
Nepali_nlp/positional_encoding.py
Nepali_nlp/preeti_unicode.py
Nepali_nlp/sentence_similar.py
Nepali_nlp/spellcheck.py
Nepali_nlp/stopword.py
Nepali_nlp/summerization.py
Nepali_nlp/synonym.py
Nepali_nlp/unicode_nepali.py
Nepali_nlp/utils.py
Nepali_nlp.egg-info/PKG-INFO
Nepali_nlp.egg-info/SOURCES.txt
Nepali_nlp.egg-info/dependency_links.txt
Nepali_nlp.egg-info/requires.txt
Nepali_nlp.egg-info/top_level.txt