Metadata-Version: 2.1
Name: Nepali-nlp
Version: 0.0.0
Summary: Natural language processing library for Nepali langauge
Home-page: https://github.com/sushil79g/Nepali_nlp
Author: ['Anish Pandey', 'Sushil Ghimire']
Author-email: sushil79g@gmail.com
License: MIT
Download-URL: https://github.com/sushil79g/Nepali_nlp/archive/v0.2.tar.gz
Project-URL: Bug Reports, https://github.com/sushil79g/Nepali_nlp/issues
Project-URL: Source, https://github.com/sushil79g/Nepali_nlp
Keywords: NLP ml ai nepali
Platform: UNKNOWN
Classifier: Programming Language :: Python :: 3
Classifier: Operating System :: OS Independent
Classifier: Development Status :: 1 - Planning
Classifier: License :: OSI Approved :: MIT License
Provides-Extra: dev
Provides-Extra: docs
Provides-Extra: testing
